scraper/Browser.py
scraper/__init__.py
scraper/scrape.py
scraper/scraper.py
scraper/search_apollo_v1.py
scraper/linkedin/__init__.py
scraper/linkedin/linkedin_scraper.py
scraper/linkedin/linkedin_scraper_v2.py
scraper/linkedin/linkedin_scraper_v3.py
scraper/models/__init__.py
scraper/models/company/Company.py
scraper/models/company/__init__.py
scraper/models/person/Education.py
scraper/models/person/Experience.py
scraper/models/person/InterestInfo.py
scraper/models/person/Person.py
scraper/models/person/Post.py
scraper/models/person/__init__.py
scraper/models/person/common.py
cometai_core-0.2.dist-info/LICENSE
cometai_core-0.2.dist-info/METADATA
cometai_core-0.2.dist-info/WHEEL
cometai_core-0.2.dist-info/top_level.txt
cometai_core-0.2.dist-info/RECORD
